fm_image_tagger/__init__.py
fm_image_tagger/__main__.py
fm_image_tagger/command_tagger.py
fm_image_tagger/display.py
fm_image_tagger/fm_image_tagger.py
fm_image_tagger/ollama_caption.py
fm_image_tagger/rename.py
fm_image_tagger/tag_edit.py
fm_image_tagger/tagger.py
fm_image_tagger/total.py
fm_image_tagger/tests/test_tag_edit.py
fm_image_tagger-0.4.2.dist-info/METADATA
fm_image_tagger-0.4.2.dist-info/WHEEL
fm_image_tagger-0.4.2.dist-info/entry_points.txt
fm_image_tagger-0.4.2.dist-info/licenses/LICENSE
fm_image_tagger-0.4.2.dist-info/RECORD
