Metadata-Version: 2.4
Name: fm_image_tagger
Version: 0.4.2
Summary: Caption tagger tool
Project-URL: Homepage, https://github.com/rerofumi/fm_image_tagger
Author-email: rerofumi <rero2@yuumu.org>
License-File: LICENSE
Classifier: Development Status :: 3 - Alpha
Classifier: Intended Audience :: Developers
Classifier: License :: OSI Approved :: MIT License
Classifier: Operating System :: OS Independent
Classifier: Programming Language :: Python :: 3
Classifier: Topic :: Multimedia :: Graphics
Requires-Python: >=3.10
Requires-Dist: click>=8.1.7
Requires-Dist: huggingface-hub>=0.25.2
Requires-Dist: numpy>=2.1.2
Requires-Dist: ollama>=0.3.3
Requires-Dist: onnxruntime>=1.19.2
Requires-Dist: pandas>=2.2.3
Requires-Dist: pillow
